fdscraper/__init__.py
fdscraper/preprocess/__init__.py
fdscraper/preprocess/preprocess_financials.py
fdscraper/preprocess/utils.py
fdscraper/score/__init__.py
fdscraper/score/score.py
fdscraper/score/utils.py
fdscraper/scrape/__init__.py
fdscraper/scrape/download.py
fdscraper/scrape/utils.py
fdscraper-0.0.1.dist-info/LICENSE.txt
fdscraper-0.0.1.dist-info/METADATA
fdscraper-0.0.1.dist-info/WHEEL
fdscraper-0.0.1.dist-info/top_level.txt
fdscraper-0.0.1.dist-info/RECORD
