Metadata-Version: 2.1
Name: fdscraper
Version: 0.0.1
Summary: A Web scrapping tool for stock fundamentals data
Home-page: https://github.com/chinmaykurade/fdscraper
Author: Chinmay Kurade
Author-email: chinmay.v.kurade@gmail.com
License: UNKNOWN
Platform: UNKNOWN
Classifier: Programming Language :: Python :: 3
Classifier: License :: OSI Approved :: MIT License
Classifier: Operating System :: OS Independent
Requires-Python: >=3.6
